README.md
setup.py
calpack/__init__.py
calpack/utils.py
calpack.egg-info/PKG-INFO
calpack.egg-info/SOURCES.txt
calpack.egg-info/dependency_links.txt
calpack.egg-info/top_level.txt
calpack/common/__init__.py
calpack/common/ip.py
calpack/models/__init__.py
calpack/models/packets.py
calpack/models/fields/ArrayFields.py
calpack/models/fields/BooleanFields.py
calpack/models/fields/Fields.py
calpack/models/fields/FloatFields.py
calpack/models/fields/IntFields.py
calpack/models/fields/PacketFields.py
calpack/models/fields/__init__.py