Metadata-Version: 2.1
Name: calpack
Version: 2018.6.0
Summary: Packets in Python made Simple
Home-page: https://github.com/KronosKoderS/CalPack
Author: KronoSKoderS
Author-email: superuser.kronos@gmail.com
License: MIT
Download-URL: https://github.com/KronosKoderS/CalPack/tarball/v2018.6.0
Platform: UNKNOWN
Classifier: License :: OSI Approved :: MIT License
Classifier: Development Status :: 4 - Beta
Classifier: Intended Audience :: Developers
Classifier: Intended Audience :: Science/Research
Classifier: Intended Audience :: System Administrators
Classifier: Intended Audience :: Telecommunications Industry
Classifier: Natural Language :: English
Classifier: Programming Language :: Python :: 2.7
Classifier: Programming Language :: Python :: 3
Classifier: Programming Language :: Python :: 3.3
Classifier: Programming Language :: Python :: 3.4
Classifier: Programming Language :: Python :: 3.5
Classifier: Programming Language :: Python :: 3.6
Classifier: Programming Language :: Python :: 3.7
Classifier: Topic :: Utilities
